onewot/__init__.py
onewot/_about.py
onewot/achievements.py
onewot/clans.py
onewot/errors.py
onewot/snowflakes.py
onewot/tanks.py
onewot/tournaments.py
onewot/urls.py
onewot/users.py
onewot/api/__init__.py
onewot/api/entity_factory.py
onewot/api/error_handlers.py
onewot/api/http.py
onewot/impl/__init__.py
onewot/impl/client.py
onewot/impl/entity_factory.py
onewot/impl/error_handlers.py
onewot/impl/http.py
onewot/internal/__init__.py
onewot/internal/data_binding.py
onewot/internal/unix.py
onewot-0.6.3.dist-info/LICENSE
onewot-0.6.3.dist-info/METADATA
onewot-0.6.3.dist-info/WHEEL
onewot-0.6.3.dist-info/top_level.txt
onewot-0.6.3.dist-info/RECORD
