Metadata-Version: 2.1
Name: onewot
Version: 0.6.3
Summary: The WotBlitz API wrapper for Python3
Home-page: https://github.com/CrispCrow/Onewot
Author: CrispCrow
Author-email: minikslyh@gmail.com
License: MIT
Project-URL: Source (GitHub), https://github.com/CrispCrow/Onewot
Project-URL: Issue Tracker, https://github.com/CrispCrow/Onewot/issues
Platform: UNKNOWN
Classifier: Programming Language :: Python :: 3.8
Classifier: Programming Language :: Python :: 3.9
Classifier: Programming Language :: Python :: Implementation :: CPython
Classifier: Natural Language :: English
Classifier: License :: OSI Approved :: MIT License
Classifier: Operating System :: OS Independent
Requires-Python: >=3.8
License-File: LICENSE
Requires-Dist: requests-futures (~=1.0.0)
Requires-Dist: attrs (~=21.4.0)
